aiotube/__init__.py
aiotube/exceptions.py
aiotube/extractors.py
aiotube/helpers.py
aiotube/itags.py
aiotube/playlist.py
aiotube/request.py
aiotube/streams.py
aiotube/video.py
aiotubes-3.5.2.dist-info/METADATA
aiotubes-3.5.2.dist-info/WHEEL
aiotubes-3.5.2.dist-info/licenses/LICENSE
aiotubes-3.5.2.dist-info/RECORD
