Metadata-Version: 2.1
Name: aiotubes
Version: 3.5.2
Summary: Asynchronous Youtube API
Project-URL: Homepage, https://github.com/sheldygg/aiotube
Author: sheldy
License-Expression: MIT
License-File: LICENSE
Classifier: Programming Language :: Python :: 3.10
Classifier: Programming Language :: Python :: 3.11
Requires-Python: >=3.10
Requires-Dist: aiohttp
Requires-Dist: pydantic
